lucid_utils/__init__.py
lucid_utils/blobbing.py
lucid_utils/cookies.txt
lucid_utils/daqmap_cluster_parse.py
lucid_utils/data_api.py
lucid_utils/frameplot.py
lucid_utils/lucidreader.py
lucid_utils/mydata.txt
lucid_utils/noisemask.py
lucid_utils/sum_frame.py
lucid_utils/tds1.txt
lucid_utils/telemetry.py
lucid_utils/xycreader.py
lucid_utils/classification/__init__.py
lucid_utils/classification/common.py
lucid_utils/classification/end_detection.py
lucid_utils/classification/least_squares_circle.py
lucid_utils/classification/lucid_algorithm.py
lucid_utils/classification/old_algorithm.py
lucid_utils/plotting/__init__.py
lucid_utils/plotting/analyse.py
lucid_utils/plotting/counts.txt
lucid_utils/plotting/geoplot.py
lucid_utils/plotting/mapmaker.py
lucid_utils/prediction/__init__.py
lucid_utils-16.10.16.dist-info/DESCRIPTION.rst
lucid_utils-16.10.16.dist-info/METADATA
lucid_utils-16.10.16.dist-info/RECORD
lucid_utils-16.10.16.dist-info/WHEEL
lucid_utils-16.10.16.dist-info/metadata.json
lucid_utils-16.10.16.dist-info/top_level.txt
